README.md
setup.py
sample/__init__.py
sample/sample.py
sna/__init__.py
sna/search.py
sna.egg-info/PKG-INFO
sna.egg-info/SOURCES.txt
sna.egg-info/dependency_links.txt
sna.egg-info/top_level.txt
test/__init__.py
test/search.py